oneNeuron/__init__.py
oneNeuron/perceptron.py
utils/__init__.py
utils/all_utils.py
one_Neuron_pypi_LijiAlex-0.0.3.dist-info/LICENSE
one_Neuron_pypi_LijiAlex-0.0.3.dist-info/METADATA
one_Neuron_pypi_LijiAlex-0.0.3.dist-info/WHEEL
one_Neuron_pypi_LijiAlex-0.0.3.dist-info/top_level.txt
one_Neuron_pypi_LijiAlex-0.0.3.dist-info/RECORD
