Metadata-Version: 2.1
Name: one-Neuron-pypi-LijiAlex
Version: 0.0.3
Summary: Perceptron Implementation
Home-page: https://github.com/LijiAlex/one_Neuron_pypi
Author: LijiAlex
Author-email: liji.alex@gmail.com
License: UNKNOWN
Project-URL: Bug Tracker, https://github.com/LijiAlex/one_Neuron_pypi/issues
Platform: UNKNOWN
Classifier: Programming Language :: Python :: 3
Classifier: License :: OSI Approved :: MIT License
Classifier: Operating System :: OS Independent
Requires-Python: >=3.7
License-File: LICENSE
Requires-Dist: numpy
Requires-Dist: tqdm
